rollo/__init__.py
rollo/__main__.py
rollo/algorithm.py
rollo/backend.py
rollo/constraints.py
rollo/evaluation.py
rollo/executor.py
rollo/input_validation.py
rollo/moltres_evaluation.py
rollo/openmc_evaluation.py
rollo/special_variables.py
rollo/toolbox_generator.py
rollo-1.0.dist-info/LICENSE
rollo-1.0.dist-info/METADATA
rollo-1.0.dist-info/WHEEL
rollo-1.0.dist-info/entry_points.txt
rollo-1.0.dist-info/top_level.txt
rollo-1.0.dist-info/RECORD
